chart_generation/__init__.py
chart_generation/__main__.py
chart_generation/chart.py
chart_generation/chart2class.py
chart_generation/charts/__init__.py
chart_generation/charts/cd-diagram.py
data_integration/__init__.py
data_integration/__main__.py
data_integration/dataset.py
data_integration/dataset2class.py
data_integration/datasets/__init__.py
data_integration/datasets/amazon.py
data_integration/datasets/book-crossing.py
data_integration/datasets/douban-movie.py
data_integration/datasets/lastfm.py
data_integration/datasets/movielens.py
data_integration/datasets/steam.py
data_integration/datasets/worker.py
data_integration/datasets/yelp.py
framework/__init__.py
framework/__main__.py
framework/experiment.py
framework/utils.py
framework/dataloader/__init__.py
framework/dataloader/dataloader.py
framework/dataloader/dataset/__init__.py
framework/dataloader/dataset/dataset.py
framework/dataloader/edge_splitter/__init__.py
framework/dataloader/edge_splitter/edge_splitter.py
framework/dataloader/graph/__init__.py
framework/dataloader/graph/graph.py
framework/dataloader/graph/node.py
framework/dataloader/preprocess/__init__.py
framework/dataloader/preprocess/methods.py
framework/evaluator/__init__.py
framework/evaluator/metric.py
framework/evaluator/metric2class.py
framework/evaluator/metrics/__init__.py
framework/evaluator/metrics/map.py
framework/evaluator/metrics/ndcg.py
framework/recommender/__init__.py
framework/recommender/model2class.py
framework/recommender/recommender.py
framework/recommender/models/__init__.py
framework/recommender/models/complEx/__init__.py
framework/recommender/models/complEx/model.py
framework/recommender/models/deep_walk_based/__init__.py
framework/recommender/models/deep_walk_based/model.py
framework/recommender/models/distMult/__init__.py
framework/recommender/models/distMult/model.py
framework/recommender/models/ePHEN/__init__.py
framework/recommender/models/ePHEN/model.py
framework/recommender/models/entity2rec/__init__.py
FranKGraphBench-0.1.1.dist-info/LICENSE
FranKGraphBench-0.1.1.dist-info/METADATA
FranKGraphBench-0.1.1.dist-info/WHEEL
FranKGraphBench-0.1.1.dist-info/entry_points.txt
FranKGraphBench-0.1.1.dist-info/top_level.txt
FranKGraphBench-0.1.1.dist-info/RECORD
