Metadata-Version: 2.1
Name: FranKGraphBench
Version: 0.1.1
Summary: pip install package for frankgraphbench.
Home-page: https://github.com/AKSW/frankgraphbench/tree/main/
Author: Paulo do Carmo and Alvaro Lopes
Author-email: paulo.carmo@htwk-leipzig.de
License: Apache-2.0
Classifier: License :: OSI Approved :: Apache Software License
Classifier: Programming Language :: Python :: 3
License-File: LICENSE
Requires-Dist: gensim
Requires-Dist: joblib
Requires-Dist: networkx ==3.1
Requires-Dist: numpy ==1.24
Requires-Dist: pandas ==2.0
Requires-Dist: python-dateutil
Requires-Dist: pytz
Requires-Dist: PyYAML
Requires-Dist: scikit-learn ==1.3
Requires-Dist: scipy ==1.10
Requires-Dist: six
Requires-Dist: smart-open
Requires-Dist: threadpoolctl
Requires-Dist: tqdm
Requires-Dist: tzdata
Requires-Dist: pykeen
Requires-Dist: torch ==2.1.2
Requires-Dist: py-cpuinfo
Requires-Dist: gputil
Requires-Dist: psutil
Requires-Dist: sentence-transformers
Requires-Dist: graph-walker
Requires-Dist: isodate ==0.6
Requires-Dist: Levenshtein ==0.21
Requires-Dist: pyparsing ==3.0
Requires-Dist: python-Levenshtein ==0.21
Requires-Dist: rapidfuzz ==3.0
Requires-Dist: rdflib ==6.3
Requires-Dist: SPARQLWrapper ==2.0
Requires-Dist: thefuzz ==0.19
Requires-Dist: tzdata ==2023.3
Requires-Dist: beautifulsoup4
Requires-Dist: matplotlib ==3.7
Requires-Dist: contourpy ==1.1
Requires-Dist: SPARQLWrapper
Requires-Dist: multiprocess
